databricks_modules_vy/__init__.py
databricks_modules_vy/data_product.py
databricks_modules_vy/data_quality_tests.py
databricks_modules_vy/dataframe.py
databricks_modules_vy/extend_class.py
databricks_modules_vy/glue.py
databricks_modules_vy/logging.py
databricks_modules_vy/oracle.py
databricks_modules_vy/qlik.py
databricks_modules_vy/s3.py
databricks_modules_vy/service_platform.py
databricks_modules_vy/sharepoint.py
databricks_modules_vy/snaplogic.py
databricks_modules_vy/styringsinfo_postgres.py
databricks_modules_vy/unity_catalog.py
databricks_modules_vy-1.1.17.dist-info/licenses/LICENSE
databricks_modules_vy-1.1.17.dist-info/METADATA
databricks_modules_vy-1.1.17.dist-info/WHEEL
databricks_modules_vy-1.1.17.dist-info/top_level.txt
databricks_modules_vy-1.1.17.dist-info/RECORD
