Metadata-Version: 2.4
Name: databricks_modules_vy
Version: 1.1.17
Summary: Databricks modules for Vy
Author-email: Sindre Kjetså <sindre.kjetsa@vy.no>
Project-URL: Homepage, https://github.com/nsbno/
Classifier: Programming Language :: Python :: 3
Classifier: License :: OSI Approved :: MIT License
Classifier: Operating System :: OS Independent
Requires-Python: >=3.8
License-File: LICENSE
Dynamic: license-file
